<?xml version="1.0" encoding="UTF-8" standalone="yes"?>
<ns2:orderDto xmlns:ns2="http://www.jje.com/schema/hotel">
	<ns2:adultNum>1</ns2:adultNum>
	<ns2:arrivalDate>2013-01-17T00:00:00+08:00</ns2:arrivalDate>
	<ns2:bookingDate>2013-01-16T16:49:14.830+08:00</ns2:bookingDate>
	<ns2:breakfastCount>0</ns2:breakfastCount>
	<ns2:cancelNeedRefund>NO</ns2:cancelNeedRefund>
	<ns2:cancelOrderCharge>0</ns2:cancelOrderCharge>
	<ns2:cancelPolicy>
		<ns2:cancelTime>30</ns2:cancelTime>
		<ns2:code>NEW_CODE</ns2:code>
		<ns2:description>请在入住前1天的18:00之前取消，逾期取消，需支付首晚房费。</ns2:description>
		<ns2:hotelId>1280</ns2:hotelId>
		<ns2:id>0</ns2:id>
		<ns2:language>ZH</ns2:language>
		<ns2:name></ns2:name>
		<ns2:penaltyType>Nights</ns2:penaltyType>
		<ns2:penaltyValue>1</ns2:penaltyValue>
		<ns2:policyType>FIRST_DAY</ns2:policyType>
	</ns2:cancelPolicy>
	<ns2:cancelRightStatus>NONE</ns2:cancelRightStatus>
	<ns2:channel>
		<ns2:code>website</ns2:code>
		<ns2:name>website</ns2:name>
	</ns2:channel>
	<ns2:checkOutDate>2013-01-18T00:00:00+08:00</ns2:checkOutDate>
	<ns2:contact>
		<ns2:email>shiqiang.luo@jinjiang.com</ns2:email>
		<ns2:mobile>13818390285</ns2:mobile>
		<ns2:name>罗世强</ns2:name>
		<ns2:phone></ns2:phone>
	</ns2:contact>
	<ns2:couponAmount>0</ns2:couponAmount>
	<ns2:creditCard />
	<ns2:firstSubOrderNo>H1D4B0D762B0$CC20130161358326160864</ns2:firstSubOrderNo>
	<ns2:flag>H1D4B0D762AF</ns2:flag>
	<ns2:guaranteePolicy>
		<ns2:code>NEW_CODE_GUARANTEE</ns2:code>
		<ns2:description>支付首晚房费，房间保留至次日12:00</ns2:description>
		<ns2:guaranteePolicyId>0</ns2:guaranteePolicyId>
		<ns2:holdtime></ns2:holdtime>
		<ns2:hotelId>1280</ns2:hotelId>
		<ns2:id>0</ns2:id>
		<ns2:language>ZH</ns2:language>
		<ns2:name></ns2:name>
		<ns2:period>DAY</ns2:period>
		<ns2:policyClass>GUARANTEE_FIRST_DAY</ns2:policyClass>
		<ns2:policyFlag>GUARANTEE</ns2:policyFlag>
		<ns2:policyType>H</ns2:policyType>
		<ns2:value>1</ns2:value>
	</ns2:guaranteePolicy>
	<ns2:guests>罗世强</ns2:guests>
	<ns2:hotel>
		<ns2:activeStatus>ACTIVE</ns2:activeStatus>
		<ns2:code>8888</ns2:code>
		<ns2:contact>
			<ns2:phone>021-61271166</ns2:phone>
		</ns2:contact>
		<ns2:hotelRating />
		<ns2:hotelRule />
		<ns2:hotelScoreType>NO</ns2:hotelScoreType>
		<ns2:id>1280</ns2:id>
		<ns2:infomation />
		<ns2:jjCode>11279</ns2:jjCode>
		<ns2:location>
			<ns2:address>上海市吴中路259号（邮编：201103）</ns2:address>
		</ns2:location>
		<ns2:name>锦江之星888888888</ns2:name>
		<ns2:origin>JJINN</ns2:origin>
		<ns2:rangePrice>
			<ns2:breakfastPrice>0</ns2:breakfastPrice>
			<ns2:doublePrice>0</ns2:doublePrice>
			<ns2:extraBedPrice>0</ns2:extraBedPrice>
			<ns2:isFreeInternet>NO</ns2:isFreeInternet>
			<ns2:quadPrice>0</ns2:quadPrice>
			<ns2:singlePrice>0</ns2:singlePrice>
			<ns2:triplePrice>0</ns2:triplePrice>
		</ns2:rangePrice>
		<ns2:scoreExchangeType>NO</ns2:scoreExchangeType>
	</ns2:hotel>
	<ns2:id>18000792</ns2:id>
	<ns2:isFreeInternet>true</ns2:isFreeInternet>
	<ns2:isIncludeService>false</ns2:isIncludeService>
	<ns2:managementStatus>NOCHECKIN</ns2:managementStatus>
	<ns2:mcMemberCode>10045</ns2:mcMemberCode>
	<ns2:member>
		<ns2:cardNo>T00002068678</ns2:cardNo>
		<ns2:cardType>J Benefit Card</ns2:cardType>
		<ns2:isPrivilege>true</ns2:isPrivilege>
		<ns2:mcMemberCode>10045</ns2:mcMemberCode>
		<ns2:name>shiqiang.luo@jinjiang.com</ns2:name>
	</ns2:member>
	<ns2:nightNum>1</ns2:nightNum>
	<ns2:operator>shiqiang.luo@jinjiang.com</ns2:operator>
	<ns2:orderDetails>
		<ns2:chargeAmount>0</ns2:chargeAmount>
		<ns2:day>2013-01-17T00:00:00+08:00</ns2:day>
		<ns2:id>6427</ns2:id>
		<ns2:orderId>18000792</ns2:orderId>
		<ns2:price>100</ns2:price>
		<ns2:taxAmount>0</ns2:taxAmount>
	</ns2:orderDetails>
	<ns2:orderNo>H1D4B0D762AF</ns2:orderNo>
	<ns2:orderOrigin>TERRACE</ns2:orderOrigin>
	<ns2:orderType>GUARANTEE</ns2:orderType>
	<ns2:paymentAmount>0</ns2:paymentAmount>
	<ns2:paymentScoreAmount>0</ns2:paymentScoreAmount>
	<ns2:plan>
		<ns2:activeStatus>ACTIVE</ns2:activeStatus>
		<ns2:cancelPolicy>
			<ns2:description></ns2:description>
			<ns2:language>ZH</ns2:language>
			<ns2:name></ns2:name>
		</ns2:cancelPolicy>
		<ns2:code>0002-SCard</ns2:code>
		<ns2:description>积分会员计划</ns2:description>
		<ns2:guaranteePolicy>
			<ns2:description></ns2:description>
			<ns2:name></ns2:name>
			<ns2:period>DAY</ns2:period>
			<ns2:policyClass>NONE</ns2:policyClass>
			<ns2:policyType>W</ns2:policyType>
		</ns2:guaranteePolicy>
		<ns2:hotel>
			<ns2:activeStatus>ACTIVE</ns2:activeStatus>
			<ns2:code>8888</ns2:code>
			<ns2:contact>
				<ns2:phone>021-61271166</ns2:phone>
			</ns2:contact>
			<ns2:hotelRating />
			<ns2:hotelRule />
			<ns2:hotelScoreType>NO</ns2:hotelScoreType>
			<ns2:id>1280</ns2:id>
			<ns2:infomation />
			<ns2:jjCode>11279</ns2:jjCode>
			<ns2:location>
				<ns2:address>上海市吴中路259号（邮编：201103）</ns2:address>
			</ns2:location>
			<ns2:name>锦江之星888888888</ns2:name>
			<ns2:origin>JJINN</ns2:origin>
			<ns2:rangePrice>
				<ns2:breakfastPrice>0</ns2:breakfastPrice>
				<ns2:doublePrice>0</ns2:doublePrice>
				<ns2:extraBedPrice>0</ns2:extraBedPrice>
				<ns2:isFreeInternet>NO</ns2:isFreeInternet>
				<ns2:quadPrice>0</ns2:quadPrice>
				<ns2:singlePrice>0</ns2:singlePrice>
				<ns2:triplePrice>0</ns2:triplePrice>
			</ns2:rangePrice>
			<ns2:scoreExchangeType>NO</ns2:scoreExchangeType>
		</ns2:hotel>
		<ns2:id>16249</ns2:id>
		<ns2:jrezStatus>ACTIVE</ns2:jrezStatus>
		<ns2:language>ZH</ns2:language>
		<ns2:name>积分会员计划</ns2:name>
		<ns2:RPI>BASE_PRICE</ns2:RPI>
		<ns2:rate>
			<ns2:code>SCard</ns2:code>
			<ns2:id>3300</ns2:id>
			<ns2:language>ZH</ns2:language>
			<ns2:name>积分会员价格码</ns2:name>
			<ns2:rateKind>N</ns2:rateKind>
			<ns2:scoreExchangeType>NO</ns2:scoreExchangeType>
		</ns2:rate>
		<ns2:room>
			<ns2:activeStatus>ACTIVE</ns2:activeStatus>
			<ns2:code>0002</ns2:code>
			<ns2:hotel>
				<ns2:activeStatus>ACTIVE</ns2:activeStatus>
				<ns2:contact />
				<ns2:hotelRating />
				<ns2:hotelRule />
				<ns2:hotelScoreType>NO</ns2:hotelScoreType>
				<ns2:infomation />
				<ns2:location />
				<ns2:rangePrice>
					<ns2:breakfastPrice>0</ns2:breakfastPrice>
					<ns2:doublePrice>0</ns2:doublePrice>
					<ns2:extraBedPrice>0</ns2:extraBedPrice>
					<ns2:isFreeInternet>NO</ns2:isFreeInternet>
					<ns2:quadPrice>0</ns2:quadPrice>
					<ns2:singlePrice>0</ns2:singlePrice>
					<ns2:triplePrice>0</ns2:triplePrice>
				</ns2:rangePrice>
				<ns2:scoreExchangeType>NO</ns2:scoreExchangeType>
			</ns2:hotel>
			<ns2:id>6197</ns2:id>
			<ns2:name>单人房A</ns2:name>
		</ns2:room>
	</ns2:plan>
	<ns2:prepaidAmount>100</ns2:prepaidAmount>
	<ns2:rate>
		<ns2:code>SCard</ns2:code>
		<ns2:id>3300</ns2:id>
		<ns2:language>ZH</ns2:language>
		<ns2:name>积分会员价格码</ns2:name>
		<ns2:rateKind>N</ns2:rateKind>
		<ns2:scoreExchangeType>NO</ns2:scoreExchangeType>
	</ns2:rate>
	<ns2:remark>809584,811542,809737</ns2:remark>
	<ns2:room>
		<ns2:activeStatus>ACTIVE</ns2:activeStatus>
		<ns2:code>0002</ns2:code>
		<ns2:hotel>
			<ns2:activeStatus>ACTIVE</ns2:activeStatus>
			<ns2:contact />
			<ns2:hotelRating />
			<ns2:hotelRule />
			<ns2:hotelScoreType>NO</ns2:hotelScoreType>
			<ns2:infomation />
			<ns2:location />
			<ns2:rangePrice>
				<ns2:breakfastPrice>0</ns2:breakfastPrice>
				<ns2:doublePrice>0</ns2:doublePrice>
				<ns2:extraBedPrice>0</ns2:extraBedPrice>
				<ns2:isFreeInternet>NO</ns2:isFreeInternet>
				<ns2:quadPrice>0</ns2:quadPrice>
				<ns2:singlePrice>0</ns2:singlePrice>
				<ns2:triplePrice>0</ns2:triplePrice>
			</ns2:rangePrice>
			<ns2:scoreExchangeType>NO</ns2:scoreExchangeType>
		</ns2:hotel>
		<ns2:id>6197</ns2:id>
		<ns2:name>单人房A</ns2:name>
	</ns2:room>
	<ns2:roomNum>1</ns2:roomNum>
	<ns2:roomPrice>100</ns2:roomPrice>
	<ns2:status>UNPAY</ns2:status>
	<ns2:thirdOrderType>GUARANTEE</ns2:thirdOrderType>
	<ns2:totalCancelCharge>0</ns2:totalCancelCharge>
	<ns2:totalChargeAmount>0</ns2:totalChargeAmount>
	<ns2:totalRoomAmount>100</ns2:totalRoomAmount>
	<ns2:updateDate>2013-01-16T16:49:14.830+08:00</ns2:updateDate>
</ns2:orderDto>
